scidb/__init__.py
scidb/scidb_pdf_get.py
colrev_scidb-0.1.0.dist-info/LICENSE
colrev_scidb-0.1.0.dist-info/METADATA
colrev_scidb-0.1.0.dist-info/WHEEL
colrev_scidb-0.1.0.dist-info/entry_points.txt
colrev_scidb-0.1.0.dist-info/RECORD
